CHANGES.txt
COPYRIGHT.txt
INSTALL.txt
LICENSE.txt
README.txt
bootstrap.py
buildout.cfg
setup.py
src/zope/__init__.py
src/zope.testrecorder.egg-info/PKG-INFO
src/zope.testrecorder.egg-info/SOURCES.txt
src/zope.testrecorder.egg-info/dependency_links.txt
src/zope.testrecorder.egg-info/namespace_packages.txt
src/zope.testrecorder.egg-info/not-zip-safe
src/zope.testrecorder.egg-info/requires.txt
src/zope.testrecorder.egg-info/top_level.txt
src/zope/testrecorder/SETUP.cfg
src/zope/testrecorder/__init__.py
src/zope/testrecorder/configure.zcml
src/zope/testrecorder/testrecorder.py
src/zope/testrecorder/zope.testrecorder-configure.zcml
src/zope/testrecorder/html/begin.html
src/zope/testrecorder/html/control.html
src/zope/testrecorder/html/doctest.html
src/zope/testrecorder/html/index.html
src/zope/testrecorder/html/recorder.js
src/zope/testrecorder/html/result.html
src/zope/testrecorder/html/selenium.html
src/zope/testrecorder/html/style.css
src/zope/testrecorder/tests/__init__.py
src/zope/testrecorder/tests/test_testrecorder.py
src/zope/testrecorder/www/addform.pt
src/zope/testrecorder/www/main.pt
src/zope/testrecorder/www/recorder.gif