Metadata-Version: 1.0
Name: zope.testrecorder
Version: 0.4
Summary: Test recorder for functional tests
Home-page: http://pypi.python.org/pypi/zope.testrecorder
Author: Zope Foundation and Contributors
Author-email: zope-dev@zope.org
License: ZPL 2.1
Keywords: web testing
Platform: UNKNOWN
Classifier: Development Status :: 5 - Production/Stable
Classifier: License :: OSI Approved :: Zope Public License
Classifier: Operating System :: OS Independent
Classifier: Topic :: Internet :: WWW/HTTP :: Browsers
Classifier: Topic :: Software Development :: Testing
